{
  "basic_data": {
    "internal_id": 80471827,
    "Award ID": "ALIF-255029-OMS-23",
    "Recipient Name": "MUSEUM OF LATIN AMERICAN ART",
    "Award Amount": 727345,
    "Total Outlays": 425462.16,
    "Description": "THE MUSEUM OF LATIN AMERICAN ART IN PARTNERSHIP WITH UNIVERSITY OF CALIFORNIA IRVINE, CALIFORNIA STATE UNIVERSITY, CALIFORNIA STATE UNIVERSITY LONG BEACH, UNIVERSITY OF CALIFORNIA LOS ANGELES, AND UNIVERSITY OF SOUTHERN CALIFORNIA–WILL DEVELOP THE LATINO MUSEUM RESEARCH AND FELLOWSHIP CONSORTIUM, A PAID FELLOWSHIP FOR MASTERS AND POSTDOCTORAL STUDENTS. PROJECT ACTIVITIES WILL INCLUDE THE CREATION OF AN ADVISORY COUNCIL TO STEER INTERNSHIP ACTIVITIES AND DEVELOP PANEL SESSIONS, PURCHASE PROFESSIONAL COLLECTIONS MANAGEMENT SOFTWARE, AND PROVIDE DIGITIZATION TRAINING. PROJECT FUNDS WILL SUPPORT FOUR PAID FELLOWS THAT WILL DIGITIZE OVER 300 OBJECTS FROM THE MUSEUM’S PERMANENT COLLECTION. THE RESULTING OUTCOME OF THE FELLOWSHIPS WILL EXPAND THE DIGITAL ARCHIVE OF THE MUSEUM’S PERMANENT COLLECTION AND CONTRIBUTE TO ACADEMIC AND CURATORIAL INQUIRY OF THE FELLOWS.",
    "Contract Award Type": "",
    "Recipient UEI": "KJGCC9MA1K15",
    "Recipient Location": {
      "address_line1": "628 ALAMITOS AVENUE",
      "address_line2": null,
      "address_line3": null,
      "city_name": "LONG BEACH",
      "congressional_code": "42",
      "country_name": "UNITED STATES",
      "county_code": "037",
      "county_name": "LOS ANGELES",
      "foreign_postal_code": null,
      "foreign_province": null,
      "location_country_code": "USA",
      "state_code": "CA",
      "state_name": "California",
      "zip4": "1513",
      "zip5": "90802"
    },
    "Primary Place of Performance": {
      "city_name": "LONG BEACH",
      "congressional_code": "42",
      "country_name": "UNITED STATES",
      "county_code": "037",
      "county_name": "LOS ANGELES",
      "location_country_code": "USA",
      "state_code": "CA",
      "state_name": "California",
      "zip4": "90802-1513",
      "zip5": "90802"
    },
    "def_codes": [
      "Q"
    ],
    "COVID-19 Obligations": 0,
    "COVID-19 Outlays": 0,
    "Infrastructure Obligations": 0,
    "Infrastructure Outlays": 0,
    "Awarding Agency": "Institute of Museum and Library Services",
    "Awarding Sub Agency": "Institute of Museum and Library Services",
    "Start Date": "2023-09-27",
    "End Date": "2026-09-30",
    "NAICS": null,
    "PSC": null,
    "recipient_id": "031e4d32-1246-6b1d-09f5-606dde7f3c4b-R",
    "prime_award_recipient_id": "",
    "generated_internal_id": "ASST_NON_ALIF-255029-OMS-23_474",
    "awarding_agency_id": 1474,
    "agency_slug": "institute-of-museum-and-library-services",
    "Loan Value": null,
    "Subsidy Cost": null,
    "Issued Date": "",
    "Funding Agency": "",
    "recipient_location_city_name": "",
    "recipient_location_state_code": "",
    "recipient_location_country_name": "",
    "recipient_location_address_line1": "",
    "pop_city_name": "",
    "pop_state_code": "",
    "pop_country_name": ""
  },
  "detailed_data": {
    "id": 80471827,
    "generated_unique_award_id": "ASST_NON_ALIF-255029-OMS-23_474",
    "piid": "",
    "category": "grant",
    "type": "04",
    "type_description": "PROJECT GRANT (B)",
    "description": "THE MUSEUM OF LATIN AMERICAN ART IN PARTNERSHIP WITH UNIVERSITY OF CALIFORNIA IRVINE, CALIFORNIA STATE UNIVERSITY, CALIFORNIA STATE UNIVERSITY LONG BEACH, UNIVERSITY OF CALIFORNIA LOS ANGELES, AND UNIVERSITY OF SOUTHERN CALIFORNIA–WILL DEVELOP THE LATINO MUSEUM RESEARCH AND FELLOWSHIP CONSORTIUM, A PAID FELLOWSHIP FOR MASTERS AND POSTDOCTORAL STUDENTS. PROJECT ACTIVITIES WILL INCLUDE THE CREATION OF AN ADVISORY COUNCIL TO STEER INTERNSHIP ACTIVITIES AND DEVELOP PANEL SESSIONS, PURCHASE PROFESSIONAL COLLECTIONS MANAGEMENT SOFTWARE, AND PROVIDE DIGITIZATION TRAINING. PROJECT FUNDS WILL SUPPORT FOUR PAID FELLOWS THAT WILL DIGITIZE OVER 300 OBJECTS FROM THE MUSEUM’S PERMANENT COLLECTION. THE RESULTING OUTCOME OF THE FELLOWSHIPS WILL EXPAND THE DIGITAL ARCHIVE OF THE MUSEUM’S PERMANENT COLLECTION AND CONTRIBUTE TO ACADEMIC AND CURATORIAL INQUIRY OF THE FELLOWS.",
    "total_obligation": 727345,
    "subaward_count": 0,
    "total_subaward_amount": null,
    "date_signed": "2023-09-15",
    "base_exercised_options": 0,
    "base_and_all_options": 0,
    "total_account_outlay": 425462.16,
    "total_account_obligation": 727345,
    "account_outlays_by_defc": [
      {
        "code": "Q",
        "amount": 425462.16
      }
    ],
    "account_obligations_by_defc": [
      {
        "code": "Q",
        "amount": 727345
      }
    ],
    "parent_award": null,
    "latest_transaction_contract_data": null,
    "funding_agency": {
      "id": 1474,
      "has_agency_page": true,
      "toptier_agency": {
        "name": "Institute of Museum and Library Services",
        "code": "474",
        "abbreviation": "IMLS",
        "slug": "institute-of-museum-and-library-services"
      },
      "subtier_agency": {
        "name": "Institute of Museum and Library Services",
        "code": "5300",
        "abbreviation": "IMLS"
      },
      "office_agency_name": "INSTITUTE OF MUSEUM  LIBRARY SVCS"
    },
    "awarding_agency": {
      "id": 1423,
      "has_agency_page": true,
      "toptier_agency": {
        "name": "Institute of Museum and Library Services",
        "code": "474",
        "abbreviation": "IMLS",
        "slug": "institute-of-museum-and-library-services"
      },
      "subtier_agency": {
        "name": "Institute of Museum and Library Services",
        "code": "5950",
        "abbreviation": "IMLS"
      },
      "office_agency_name": "INSTITUTE OF MUSEUM  LIBRARY SVCS"
    },
    "period_of_performance": {
      "start_date": "2023-09-27",
      "end_date": "2026-09-30",
      "last_modified_date": "2023-09-20",
      "potential_end_date": ""
    },
    "recipient": {
      "recipient_hash": "031e4d32-1246-6b1d-09f5-606dde7f3c4b-R",
      "recipient_name": "MUSEUM OF LATIN AMERICAN ART",
      "recipient_uei": "KJGCC9MA1K15",
      "recipient_unique_id": null,
      "parent_recipient_hash": "",
      "parent_recipient_name": "",
      "parent_recipient_uei": "",
      "parent_recipient_unique_id": null,
      "business_categories": [
        "Government",
        "U.S. Regional/State Government"
      ],
      "location": {
        "location_country_code": "USA",
        "country_name": "UNITED STATES",
        "state_code": "CA",
        "state_name": "CALIFORNIA",
        "city_name": "LONG BEACH",
        "county_code": "037",
        "county_name": "LOS ANGELES",
        "address_line1": "628 ALAMITOS AVENUE",
        "address_line2": null,
        "address_line3": null,
        "congressional_code": "42",
        "zip4": "1513",
        "zip5": "90802",
        "foreign_postal_code": null,
        "foreign_province": null
      }
    },
    "executive_details": {
      "officers": [
        {
          "name": null,
          "amount": null
        },
        {
          "name": null,
          "amount": null
        },
        {
          "name": null,
          "amount": null
        },
        {
          "name": null,
          "amount": null
        },
        {
          "name": null,
          "amount": null
        }
      ]
    },
    "place_of_performance": {
      "location_country_code": "USA",
      "country_name": "UNITED STATES",
      "state_code": "CA",
      "state_name": "CALIFORNIA",
      "city_name": "LONG BEACH",
      "county_code": "037",
      "county_name": "LOS ANGELES",
      "address_line1": "",
      "address_line2": null,
      "address_line3": null,
      "congressional_code": "42",
      "zip4": "1513",
      "zip5": "90802",
      "foreign_postal_code": null,
      "foreign_province": null
    },
    "psc_hierarchy": {
      "toptier_code": {
        "code": "",
        "description": ""
      },
      "midtier_code": {
        "code": "",
        "description": ""
      },
      "subtier_code": null,
      "base_code": {
        "code": "",
        "description": ""
      }
    },
    "naics_hierarchy": {
      "toptier_code": {
        "code": "",
        "description": ""
      },
      "midtier_code": {
        "code": "",
        "description": ""
      },
      "base_code": {
        "code": "",
        "description": ""
      }
    },
    "total_outlay": 425462.16
  }
}
