{
  "basic_data": {
    "internal_id": 87755104,
    "Award ID": "FG02-04ER54739",
    "Recipient Name": "UNIVERSITY OF CALIFORNIA, BERKELEY",
    "Award Amount": 2086000,
    "Total Outlays": null,
    "Description": "TURBULENCE, STRUCTURES, AND MACROSCOPIC TRANSPORT IN EDGE, SOL AND DIVERTOR PLASMAS",
    "Contract Award Type": "",
    "Recipient UEI": "FC61S8K9AGX8",
    "Recipient Location": {
      "address_line1": null,
      "address_line2": null,
      "address_line3": null,
      "city_name": "LA JOLLA",
      "congressional_code": "49",
      "country_name": null,
      "county_code": "059",
      "county_name": "ORANGE",
      "foreign_postal_code": null,
      "foreign_province": null,
      "location_country_code": "USA",
      "state_code": "CA",
      "state_name": "California",
      "zip4": "0934",
      "zip5": "92093"
    },
    "Primary Place of Performance": {
      "city_name": "LA JOLLA",
      "congressional_code": "49",
      "country_name": null,
      "county_code": null,
      "county_name": null,
      "location_country_code": "USA",
      "state_code": "CA",
      "state_name": "California",
      "zip4": "920930934",
      "zip5": null
    },
    "def_codes": null,
    "COVID-19 Obligations": null,
    "COVID-19 Outlays": null,
    "Infrastructure Obligations": null,
    "Infrastructure Outlays": null,
    "Awarding Agency": "Department of Energy",
    "Awarding Sub Agency": "Department of Energy",
    "Start Date": "2004-02-18",
    "End Date": "2012-01-14",
    "NAICS": null,
    "PSC": null,
    "recipient_id": "6ce06351-42d9-5b7b-d142-1b22e4cb47b0-C",
    "prime_award_recipient_id": "",
    "generated_internal_id": "ASST_NON_FG02-04ER54739_089",
    "awarding_agency_id": 930,
    "agency_slug": "department-of-energy",
    "Loan Value": null,
    "Subsidy Cost": null,
    "Issued Date": "",
    "Funding Agency": "",
    "recipient_location_city_name": "",
    "recipient_location_state_code": "",
    "recipient_location_country_name": "",
    "recipient_location_address_line1": "",
    "pop_city_name": "",
    "pop_state_code": "",
    "pop_country_name": ""
  },
  "detailed_data": {
    "id": 87755104,
    "generated_unique_award_id": "ASST_NON_FG02-04ER54739_089",
    "piid": "",
    "category": "grant",
    "type": "04",
    "type_description": "",
    "description": "TURBULENCE, STRUCTURES, AND MACROSCOPIC TRANSPORT IN EDGE, SOL AND DIVERTOR PLASMAS",
    "total_obligation": 2086000,
    "subaward_count": 0,
    "total_subaward_amount": null,
    "date_signed": "2004-02-18",
    "base_exercised_options": 0,
    "base_and_all_options": 0,
    "total_account_outlay": 0,
    "total_account_obligation": 0,
    "account_outlays_by_defc": [],
    "account_obligations_by_defc": [],
    "parent_award": null,
    "latest_transaction_contract_data": null,
    "funding_agency": {
      "id": 0,
      "has_agency_page": false,
      "toptier_agency": {
        "name": "",
        "code": "",
        "abbreviation": "",
        "slug": ""
      },
      "subtier_agency": {
        "name": "",
        "code": "",
        "abbreviation": ""
      },
      "office_agency_name": ""
    },
    "awarding_agency": {
      "id": 930,
      "has_agency_page": true,
      "toptier_agency": {
        "name": "Department of Energy",
        "code": "089",
        "abbreviation": "DOE",
        "slug": "department-of-energy"
      },
      "subtier_agency": {
        "name": "Department of Energy",
        "code": "8900",
        "abbreviation": "DOE"
      },
      "office_agency_name": ""
    },
    "period_of_performance": {
      "start_date": "2004-02-18",
      "end_date": "2012-01-14",
      "last_modified_date": "2011-09-07",
      "potential_end_date": ""
    },
    "recipient": {
      "recipient_hash": "6ce06351-42d9-5b7b-d142-1b22e4cb47b0-R",
      "recipient_name": "UNIVERSITY OF CALIFORNIA, BERKELEY",
      "recipient_uei": "FC61S8K9AGX8",
      "recipient_unique_id": "626001135",
      "parent_recipient_hash": "",
      "parent_recipient_name": "",
      "parent_recipient_uei": "",
      "parent_recipient_unique_id": null,
      "business_categories": [
        "Higher Education",
        "Higher Education (Public)"
      ],
      "location": {
        "location_country_code": "",
        "country_name": "",
        "state_code": "CA",
        "state_name": "CALIFORNIA",
        "city_name": "LA JOLLA",
        "county_code": "059",
        "county_name": "ORANGE",
        "address_line1": "",
        "address_line2": null,
        "address_line3": null,
        "congressional_code": "50",
        "zip4": "0934",
        "zip5": "92093",
        "foreign_postal_code": null,
        "foreign_province": null
      }
    },
    "executive_details": {
      "officers": [
        {
          "name": null,
          "amount": null
        },
        {
          "name": null,
          "amount": null
        },
        {
          "name": null,
          "amount": null
        },
        {
          "name": null,
          "amount": null
        },
        {
          "name": null,
          "amount": null
        }
      ]
    },
    "place_of_performance": {
      "location_country_code": "",
      "country_name": "",
      "state_code": "CA",
      "state_name": "CALIFORNIA",
      "city_name": "LA JOLLA",
      "county_code": "",
      "county_name": "",
      "address_line1": "",
      "address_line2": null,
      "address_line3": null,
      "congressional_code": "",
      "zip4": "",
      "zip5": "",
      "foreign_postal_code": null,
      "foreign_province": null
    },
    "psc_hierarchy": {
      "toptier_code": {
        "code": "",
        "description": ""
      },
      "midtier_code": {
        "code": "",
        "description": ""
      },
      "subtier_code": null,
      "base_code": {
        "code": "",
        "description": ""
      }
    },
    "naics_hierarchy": {
      "toptier_code": {
        "code": "",
        "description": ""
      },
      "midtier_code": {
        "code": "",
        "description": ""
      },
      "base_code": {
        "code": "",
        "description": ""
      }
    },
    "total_outlay": 0
  }
}
